syngenta_digital_dbv/__init__.py
syngenta_digital_dbv/common/__init__.py
syngenta_digital_dbv/common/config.py
syngenta_digital_dbv/common/directory_scanner.py
syngenta_digital_dbv/mongo/__init__.py
syngenta_digital_dbv/mongo/versioner.py
syngenta_digital_dbv/postgres/__init__.py
syngenta_digital_dbv/postgres/sql_connector.py
syngenta_digital_dbv/postgres/versioner.py
tests/__init__.py
tests/syngenta_digital_dbv/__init__.py
tests/syngenta_digital_dbv/test__init__.py
tests/syngenta_digital_dbv/test_get_ssm_param.py
syngenta_digital_dbv-0.0.9.dist-info/LICENSE
syngenta_digital_dbv-0.0.9.dist-info/METADATA
syngenta_digital_dbv-0.0.9.dist-info/WHEEL
syngenta_digital_dbv-0.0.9.dist-info/top_level.txt
syngenta_digital_dbv-0.0.9.dist-info/RECORD
